{"gallery_items": [
	{
		"url" : "posts/2016/12/30/_DSC4276.JPG",
		"title" : "SYLWESTROWO",
        	"type" : "image"
	},
	{
		"url" : "posts/2016/12/30/_DSC4269.JPG",
		"title" : "SYLWESTROWO",
        	"type" : "image"
	},
	{
		"url" : "posts/2016/12/30/_DSC4277.JPG",
		"title" : "SYLWESTROWO",
        	"type" : "image"
	},
	{
		"url" : "posts/2016/12/30/_DSC4280.JPG",
		"title" : "SYLWESTROWO",
        	"type" : "image"
	},
	{
		"url" : "posts/2016/12/30/_DSC4282.JPG",
		"title" : "SYLWESTROWO",
        	"type" : "image"
	},
	{
		"url" : "posts/2016/12/30/_DSC4271.JPG",
		"title" : "SYLWESTROWO",
        	"type" : "image"
	},
	{
		"url" : "posts/2016/12/30/_DSC4272.JPG",
		"title" : "SYLWESTROWO",
        	"type" : "image"
	},
	{
		"url" : "posts/2016/12/30/_DSC4274.JPG",
		"title" : "SYLWESTROWO",
        	"type" : "image"
	},
	{
		"url" : "posts/2016/12/30/_DSC4274s.jpg",
		"title" : "SYLWESTROWO",
        	"type" : "image"
	},
	{
		"url" : "posts/2016/12/30/_DSC4285.JPG",
		"title" : "SYLWESTROWO",
        	"type" : "image"
	},
	{
		"url" : "posts/2016/12/30/diamond.png",
		"title" : "SYLWESTROWO",
        	"type" : "image"
	},
	{
		"url" : "posts/2016/12/30/txt.html",
		"title" : "SYLWESTROWO",
		"type" : "ajax"
	}
]
}













